vijsamplepackage/__init__.py
vijsamplepackage/functions.py
vijsamplepackage/greet.py
vijsamplepackage-0.0.5.dist-info/METADATA
vijsamplepackage-0.0.5.dist-info/WHEEL
vijsamplepackage-0.0.5.dist-info/top_level.txt
vijsamplepackage-0.0.5.dist-info/RECORD
